aioipfs/__init__.py
aioipfs/api.py
aioipfs/exceptions.py
aioipfs/helpers.py
aioipfs/multi.py
aioipfs/util.py
aioipfs/apis/__init__.py
aioipfs/apis/dag.py
aioipfs/apis/multibase.py
aioipfs/apis/p2p.py
aioipfs/apis/pin.py
aioipfs/apis/pubsub.py
aioipfs/apis/swarm.py
aioipfs/scripts/__init__.py
aioipfs/scripts/bohort/__init__.py
aioipfs/scripts/bohort/cli.py
aioipfs/scripts/bohort/default_config.yaml
byteforge_aioipfs-0.8.1.dist-info/licenses/LICENSE
byteforge_aioipfs-0.8.1.dist-info/METADATA
byteforge_aioipfs-0.8.1.dist-info/WHEEL
byteforge_aioipfs-0.8.1.dist-info/entry_points.txt
byteforge_aioipfs-0.8.1.dist-info/top_level.txt
byteforge_aioipfs-0.8.1.dist-info/RECORD
